nikipy2021/__init__.py
nikipy2021/lib2.py
nikipy2021-0.1.dist-info/METADATA
nikipy2021-0.1.dist-info/WHEEL
nikipy2021-0.1.dist-info/top_level.txt
nikipy2021-0.1.dist-info/RECORD
