Metadata-Version: 2.1
Name: nikipy2021
Version: 0.1
Summary: Taiwan No. 1
Home-page: http://github.com/storborg/funniest
Author: niki7120
Author-email: niki.a7821@gmail.com
License: 2Lriioai
Platform: UNKNOWN
